topsis/__init__.py
topsis/topsis.py
Topsis_Manpreet_102003171-0.0.3.dist-info/License.txt
Topsis_Manpreet_102003171-0.0.3.dist-info/METADATA
Topsis_Manpreet_102003171-0.0.3.dist-info/WHEEL
Topsis_Manpreet_102003171-0.0.3.dist-info/entry_points.txt
Topsis_Manpreet_102003171-0.0.3.dist-info/top_level.txt
Topsis_Manpreet_102003171-0.0.3.dist-info/RECORD
