Metadata-Version: 2.1
Name: Topsis-Manpreet-102003171
Version: 0.0.3
Summary: Calculates Topsis Score and Rank them accordingly
Author: Manpreet Singh
Author-email: manpreetchahal0786@gmail.com
License: MIT
Classifier: Programming Language :: Python :: 3
Classifier: License :: OSI Approved :: MIT License
Classifier: Operating System :: OS Independent
License-File: License.txt
Requires-Dist: pandas
